{"type":"PDC","number":"383","year":"1993","date":"15/12/1993","author":"COMISSÃO MISTA DO ENDIVIDAMENTO AGRÍCOLA","amendment":"Susta a aplicação do disposto na Resolução nº 590 de 07/12/79, do Conselho Monetário Nacional, e todos os atos decorrentes e correlatos (AUTOR: CPMI, Destinada a investigar as causas do endividamento do setor agrícola, o elevado custo dos seus financiamentos e as condições de importação de alimentos nos exercícios de 1990 a 1993).","tags":"Sustação, aplicação, dispositivos, Resolução, Conselho Monetário Nacional, autorização,\r\ncobrança, correção monetária, capitalização, juros, juro de mora, encargo, adicionais, inadimplência, refinanciamento, dívida, contratação, financiamento, mutuário, anterioridade, quitação, débitos, aplicação, empréstimo, operação financeira, crédito rural.\r\n","status":"Diversas","rollCalls":[{"datetime":"1994-02-02T15:46:00.000Z","obj":"","summary":"","votes":[{"deputyID":24,"vote":0,"party":"PTB"},{"deputyID":1088,"vote":0,"party":"PP"},{"deputyID":347,"vote":0,"party":"PMDB"},{"deputyID":25,"vote":0,"party":"PP"},{"deputyID":349,"vote":0,"party":"PFL"},{"deputyID":27,"vote":0,"party":"PPR"},{"deputyID":28,"vote":0,"party":"PFL"},{"deputyID":30,"vote":1,"party":"PT"},{"deputyID":350,"vote":0,"party":"PFL"},{"deputyID":351,"vote":0,"party":"PFL"},{"deputyID":1,"vote":0,"party":"PTB"},{"deputyID":352,"vote":0,"party":"PMDB"},{"deputyID":353,"vote":0,"party":"PPR"},{"deputyID":32,"vote":0,"party":"PTB"},{"deputyID":356,"vote":0,"party":"PP"},{"deputyID":37,"vote":0,"party":"PDT"},{"deputyID":359,"vote":0,"party":"PFL"},{"deputyID":1126,"vote":1,"party":"PFL"},{"deputyID":1127,"vote":0,"party":"PSD"},{"deputyID":40,"vote":0,"party":"PP"},{"deputyID":45,"vote":0,"party":"PPR"},{"deputyID":46,"vote":1,"party":"PMDB"},{"deputyID":363,"vote":0,"party":"PMDB"},{"deputyID":1091,"vote":0,"party":"PMDB"},{"deputyID":365,"vote":0,"party":"PPR"},{"deputyID":49,"vote":0,"party":"PFL"},{"deputyID":53,"vote":1,"party":"PP"},{"deputyID":54,"vote":1,"party":"PT"},{"deputyID":671,"vote":1,"party":"PSDB"},{"deputyID":366,"vote":0,"party":"PPR"},{"deputyID":56,"vote":1,"party":"PPR"},{"deputyID":57,"vote":0,"party":"PFL"},{"deputyID":63,"vote":0,"party":"PP"},{"deputyID":368,"vote":0,"party":"PFL"},{"deputyID":64,"vote":1,"party":"PSDB"},{"deputyID":65,"vote":0,"party":"PMDB"},{"deputyID":66,"vote":1,"party":"PSDB"},{"deputyID":67,"vote":0,"party":"PP"},{"deputyID":69,"vote":1,"party":"PSDB"},{"deputyID":71,"vote":0,"party":"PDT"},{"deputyID":72,"vote":1,"party":"PSDB"},{"deputyID":1095,"vote":0,"party":"PFL"},{"deputyID":75,"vote":1,"party":"PSDB"},{"deputyID":77,"vote":0,"party":"PP"},{"deputyID":369,"vote":0,"party":"PFL"},{"deputyID":370,"vote":0,"party":"PMDB"},{"deputyID":372,"vote":0,"party":"PMDB"},{"deputyID":82,"vote":0,"party":"PPR"},{"deputyID":374,"vote":0,"party":"PMDB"},{"deputyID":84,"vote":0,"party":"PMDB"},{"deputyID":375,"vote":0,"party":"PFL"},{"deputyID":1128,"vote":0,"party":"PDT"},{"deputyID":87,"vote":0,"party":"PPR"},{"deputyID":378,"vote":0,"party":"PFL"},{"deputyID":379,"vote":0,"party":"PMDB"},{"deputyID":88,"vote":0,"party":"PMDB"},{"deputyID":1097,"vote":0,"party":"PMDB"},{"deputyID":89,"vote":1,"party":"PSB"},{"deputyID":5,"vote":0,"party":"PFL"},{"deputyID":460,"vote":0,"party":"PFL"},{"deputyID":472,"vote":0,"party":"PFL"},{"deputyID":885,"vote":0,"party":"PFL"},{"deputyID":92,"vote":1,"party":"PSB"},{"deputyID":383,"vote":0,"party":"PSDB"},{"deputyID":93,"vote":0,"party":"PFL"},{"deputyID":94,"vote":1,"party":"PSB"},{"deputyID":95,"vote":0,"party":"PMDB"},{"deputyID":384,"vote":0,"party":"PFL"},{"deputyID":451,"vote":0,"party":"PFL"},{"deputyID":96,"vote":0,"party":"PCdoB"},{"deputyID":97,"vote":1,"party":"PSB"},{"deputyID":454,"vote":1,"party":"PSB"},{"deputyID":385,"vote":1,"party":"PSDB"},{"deputyID":101,"vote":0,"party":"PMDB"},{"deputyID":7,"vote":0,"party":"PTB"},{"deputyID":392,"vote":0,"party":"PFL"},{"deputyID":104,"vote":0,"party":"PPR"},{"deputyID":394,"vote":0,"party":"PFL"},{"deputyID":106,"vote":0,"party":"PFL"},{"deputyID":395,"vote":0,"party":"PFL"},{"deputyID":107,"vote":2,"party":"PSDB"},{"deputyID":108,"vote":0,"party":"PSDB"},{"deputyID":396,"vote":0,"party":"PFL"},{"deputyID":109,"vote":2,"party":"PTB"},{"deputyID":110,"vote":1,"party":"PSDB"},{"deputyID":113,"vote":1,"party":"PCdoB"},{"deputyID":114,"vote":1,"party":"PT"},{"deputyID":397,"vote":0,"party":"PMDB"},{"deputyID":399,"vote":0,"party":"PFL"},{"deputyID":401,"vote":0,"party":"PL"},{"deputyID":118,"vote":1,"party":"PFL"},{"deputyID":120,"vote":0,"party":"PFL"},{"deputyID":121,"vote":0,"party":"PFL"},{"deputyID":122,"vote":1,"party":"PT"},{"deputyID":483,"vote":0,"party":"PP"},{"deputyID":403,"vote":0,"party":"PMDB"},{"deputyID":124,"vote":0,"party":"PMDB"},{"deputyID":125,"vote":1,"party":"PSDB"},{"deputyID":1099,"vote":1,"party":"PSB"},{"deputyID":126,"vote":1,"party":"PT"},{"deputyID":127,"vote":0,"party":"PMDB"},{"deputyID":132,"vote":0,"party":"PMDB"},{"deputyID":133,"vote":0,"party":"PMDB"},{"deputyID":134,"vote":0,"party":"PL"},{"deputyID":136,"vote":0,"party":"PPR"},{"deputyID":1129,"vote":2,"party":"PSD"},{"deputyID":10,"vote":1,"party":"PTB"},{"deputyID":140,"vote":1,"party":"PSDB"},{"deputyID":1081,"vote":0,"party":"PFL"},{"deputyID":143,"vote":0,"party":"PFL"},{"deputyID":146,"vote":0,"party":"PMDB"},{"deputyID":11,"vote":0,"party":"PP"},{"deputyID":513,"vote":0,"party":"PL"},{"deputyID":148,"vote":0,"party":"PP"},{"deputyID":149,"vote":1,"party":"PSDB"},{"deputyID":150,"vote":1,"party":"PSDB"},{"deputyID":151,"vote":1,"party":"PT"},{"deputyID":152,"vote":1,"party":"PTB"},{"deputyID":405,"vote":0,"party":"PMDB"},{"deputyID":406,"vote":0,"party":"PP"},{"deputyID":407,"vote":0,"party":"PPR"},{"deputyID":153,"vote":1,"party":"PT"},{"deputyID":154,"vote":1,"party":"PSDB"},{"deputyID":157,"vote":0,"party":"PSDB"},{"deputyID":159,"vote":0,"party":"PTB"},{"deputyID":160,"vote":0,"party":"PMDB"},{"deputyID":162,"vote":0,"party":"PTB"},{"deputyID":165,"vote":0,"party":"PMDB"},{"deputyID":167,"vote":0,"party":"PMDB"},{"deputyID":168,"vote":0,"party":"PMDB"},{"deputyID":170,"vote":0,"party":"PFL"},{"deputyID":506,"vote":0,"party":"PFL"},{"deputyID":172,"vote":1,"party":"PT"},{"deputyID":173,"vote":0,"party":"PDT"},{"deputyID":1101,"vote":0,"party":"PDT"},{"deputyID":176,"vote":0,"party":"PPR"},{"deputyID":177,"vote":0,"party":"PPR"},{"deputyID":178,"vote":1,"party":"PSB"},{"deputyID":180,"vote":0,"party":"PTB"},{"deputyID":181,"vote":0,"party":"PDT"},{"deputyID":182,"vote":0,"party":"PL"},{"deputyID":410,"vote":0,"party":"PDT"},{"deputyID":938,"vote":0,"party":"PDT"},{"deputyID":183,"vote":0,"party":"PDT"},{"deputyID":184,"vote":1,"party":"PL"},{"deputyID":529,"vote":2,"party":"PP"},{"deputyID":186,"vote":1,"party":"PSDB"},{"deputyID":188,"vote":0,"party":"PP"},{"deputyID":191,"vote":0,"party":"PPR"},{"deputyID":193,"vote":1,"party":"PV"},{"deputyID":195,"vote":0,"party":"PDT"},{"deputyID":196,"vote":1,"party":"PT"},{"deputyID":198,"vote":0,"party":"PSD"},{"deputyID":412,"vote":0,"party":"PP"},{"deputyID":413,"vote":2,"party":"PMDB"},{"deputyID":199,"vote":1,"party":"PT"},{"deputyID":13,"vote":0,"party":"PPR"},{"deputyID":202,"vote":0,"party":"PMDB"},{"deputyID":203,"vote":0,"party":"PL"},{"deputyID":205,"vote":1,"party":"PT"},{"deputyID":208,"vote":1,"party":"PSDB"},{"deputyID":209,"vote":0,"party":"PPR"},{"deputyID":210,"vote":0,"party":"PL"},{"deputyID":211,"vote":1,"party":"PT"},{"deputyID":212,"vote":1,"party":"PSDB"},{"deputyID":213,"vote":0,"party":"PPR"},{"deputyID":215,"vote":1,"party":"PT"},{"deputyID":216,"vote":1,"party":"PT"},{"deputyID":1130,"vote":2,"party":"PL"},{"deputyID":416,"vote":0,"party":"PFL"},{"deputyID":217,"vote":0,"party":"PMDB"},{"deputyID":218,"vote":1,"party":"PCdoB"},{"deputyID":220,"vote":1,"party":"PT"},{"deputyID":15,"vote":1,"party":"PT"},{"deputyID":221,"vote":1,"party":"PSDB"},{"deputyID":222,"vote":0,"party":"PDT"},{"deputyID":223,"vote":0,"party":"PPR"},{"deputyID":224,"vote":0,"party":"PP"},{"deputyID":226,"vote":1,"party":"PSDB"},{"deputyID":228,"vote":1,"party":"PSDB"},{"deputyID":230,"vote":1,"party":"PT"},{"deputyID":231,"vote":0,"party":"PPR"},{"deputyID":233,"vote":0,"party":"PMDB"},{"deputyID":234,"vote":0,"party":"PTB"},{"deputyID":235,"vote":0,"party":"PMDB"},{"deputyID":236,"vote":0,"party":"PPR"},{"deputyID":239,"vote":0,"party":"PPR"},{"deputyID":581,"vote":0,"party":"PL"},{"deputyID":582,"vote":0,"party":"PMDB"},{"deputyID":241,"vote":0,"party":"PMDB"},{"deputyID":244,"vote":0,"party":"PFL"},{"deputyID":245,"vote":0,"party":"PMDB"},{"deputyID":246,"vote":0,"party":"PTB"},{"deputyID":418,"vote":0,"party":"PL"},{"deputyID":248,"vote":1,"party":"PPS"},{"deputyID":249,"vote":0,"party":"PP"},{"deputyID":251,"vote":1,"party":"PSDB"},{"deputyID":253,"vote":0,"party":"PFL"},{"deputyID":255,"vote":1,"party":"PSDB"},{"deputyID":258,"vote":0,"party":"PMDB"},{"deputyID":260,"vote":0,"party":"PPR"},{"deputyID":261,"vote":0,"party":"PP"},{"deputyID":262,"vote":0,"party":"PMDB"},{"deputyID":263,"vote":0,"party":"PPR"},{"deputyID":420,"vote":0,"party":"PPR"},{"deputyID":265,"vote":0,"party":"PFL"},{"deputyID":266,"vote":0,"party":"PMDB"},{"deputyID":267,"vote":0,"party":"PTB"},{"deputyID":422,"vote":0,"party":"PFL"},{"deputyID":270,"vote":0,"party":"PMDB"},{"deputyID":271,"vote":0,"party":"PFL"},{"deputyID":274,"vote":0,"party":"PDT"},{"deputyID":424,"vote":0,"party":"PP"},{"deputyID":275,"vote":0,"party":"PP"},{"deputyID":276,"vote":1,"party":"PT"},{"deputyID":277,"vote":0,"party":"PSD"},{"deputyID":425,"vote":0,"party":"PDT"},{"deputyID":278,"vote":1,"party":"PSDB"},{"deputyID":427,"vote":0,"party":"PFL"},{"deputyID":279,"vote":0,"party":"PMDB"},{"deputyID":609,"vote":0,"party":"PFL"},{"deputyID":19,"vote":0,"party":"PP"},{"deputyID":280,"vote":0,"party":"PSD"},{"deputyID":282,"vote":0,"party":"PPR"},{"deputyID":284,"vote":1,"party":"PSDB"},{"deputyID":285,"vote":1,"party":"PT"},{"deputyID":1131,"vote":0,"party":"PFL"},{"deputyID":429,"vote":0,"party":"PMDB"},{"deputyID":290,"vote":0,"party":"PDT"},{"deputyID":291,"vote":0,"party":"PPR"},{"deputyID":292,"vote":1,"party":"PT"},{"deputyID":293,"vote":0,"party":"PMDB"},{"deputyID":431,"vote":0,"party":"PFL"},{"deputyID":294,"vote":0,"party":"PMDB"},{"deputyID":295,"vote":0,"party":"PPR"},{"deputyID":299,"vote":1,"party":"PT"},{"deputyID":300,"vote":0,"party":"PPR"},{"deputyID":302,"vote":2,"party":"PPR"},{"deputyID":432,"vote":0,"party":"PDT"},{"deputyID":304,"vote":0,"party":"PMDB"},{"deputyID":602,"vote":0,"party":"PDT"},{"deputyID":306,"vote":2,"party":"PPR"},{"deputyID":307,"vote":0,"party":"PPR"},{"deputyID":310,"vote":0,"party":"PDT"},{"deputyID":311,"vote":0,"party":"PMDB"},{"deputyID":312,"vote":0,"party":"PMDB"},{"deputyID":433,"vote":0,"party":"PMDB"},{"deputyID":314,"vote":2,"party":"PT"},{"deputyID":315,"vote":0,"party":"PMDB"},{"deputyID":434,"vote":0,"party":"PMDB"},{"deputyID":317,"vote":0,"party":"PMDB"},{"deputyID":318,"vote":0,"party":"PPR"},{"deputyID":319,"vote":1,"party":"PT"},{"deputyID":320,"vote":0,"party":"PPR"},{"deputyID":322,"vote":0,"party":"PPR"},{"deputyID":323,"vote":0,"party":"PDT"},{"deputyID":1072,"vote":0,"party":"PPR"},{"deputyID":324,"vote":0,"party":"PP"},{"deputyID":438,"vote":1,"party":"PSDB"},{"deputyID":328,"vote":0,"party":"PDT"},{"deputyID":23,"vote":0,"party":"PMDB"},{"deputyID":439,"vote":0,"party":"PFL"},{"deputyID":331,"vote":0,"party":"PTB"},{"deputyID":492,"vote":0,"party":"PMDB"},{"deputyID":332,"vote":0,"party":"PTB"},{"deputyID":344,"vote":0,"party":"PSC"},{"deputyID":569,"vote":0,"party":"PMDB"},{"deputyID":1132,"vote":0,"party":"PMDB"},{"deputyID":617,"vote":0,"party":"PMDB"},{"deputyID":1045,"vote":0,"party":"PMDB"},{"deputyID":696,"vote":0,"party":"PPR"},{"deputyID":597,"vote":0,"party":"PFL"},{"deputyID":1105,"vote":1,"party":"PSDB"},{"deputyID":1052,"vote":1,"party":"PSDB"},{"deputyID":1107,"vote":0,"party":"PMDB"},{"deputyID":1108,"vote":1,"party":"PT"},{"deputyID":1109,"vote":0,"party":"PDT"},{"deputyID":1133,"vote":0,"party":"PSDB"},{"deputyID":614,"vote":1,"party":"PT"},{"deputyID":1111,"vote":0,"party":"PPR"},{"deputyID":1113,"vote":0,"party":"PMDB"},{"deputyID":494,"vote":1,"party":"PCdoB"},{"deputyID":1115,"vote":0,"party":"PL"},{"deputyID":1134,"vote":1,"party":"PSDB"}]}]}