{"type":"PDC","number":"471","year":"2011","date":"30/09/2011","author":"Representação Brasileira no Parlamento do Mercosul.","amendment":"Aprova o texto da Decisão CMC nº 63, de 2010, \"Alto Representante-Geral do Mercosul\", aprovada na XL Reunião Ordinária do Conselho do Mercado Comum, realizada em Foz do Iguaçu, Paraná, em 16 de dezembro de 2010\".","tags":"Aprovação, decisão, Mercosul, criação, cargo, representante. ","status":"Tranformada no(a) Decreto Legislativo 304/2013","rollCalls":[{"datetime":"2013-02-28T14:07:00.000Z","obj":"REQUERIMENTO DE RETIRADA DE PAUTA","summary":"Prejudicado o Requerimento por falta de \"quorum\" (Obstrução). Sim: 4; não: 13; abstenção: 6; total: 23.","votes":[{"deputyID":1798,"vote":1,"party":"PRB"},{"deputyID":1189,"vote":3,"party":"PMDB"},{"deputyID":1261,"vote":2,"party":"PT"},{"deputyID":1664,"vote":3,"party":"PR"},{"deputyID":1210,"vote":2,"party":"PSD"},{"deputyID":847,"vote":3,"party":"PMDB"},{"deputyID":1978,"vote":3,"party":"PDT"},{"deputyID":1669,"vote":2,"party":"PMDB"},{"deputyID":1434,"vote":3,"party":"PSD"},{"deputyID":1681,"vote":3,"party":"PMDB"},{"deputyID":565,"vote":3,"party":"PT"},{"deputyID":85,"vote":1,"party":"PR"},{"deputyID":1843,"vote":1,"party":"PSB"},{"deputyID":1693,"vote":3,"party":"PT"},{"deputyID":1694,"vote":3,"party":"PT"},{"deputyID":1703,"vote":3,"party":"PT"},{"deputyID":605,"vote":1,"party":"PR"},{"deputyID":1635,"vote":3,"party":"PT"},{"deputyID":1474,"vote":3,"party":"PMDB"},{"deputyID":1282,"vote":1,"party":"PSOL"},{"deputyID":608,"vote":1,"party":"PMDB"},{"deputyID":175,"vote":1,"party":"PP"},{"deputyID":1723,"vote":3,"party":"PDT"},{"deputyID":191,"vote":3,"party":"PDT"},{"deputyID":1017,"vote":3,"party":"DEM"},{"deputyID":188,"vote":4,"party":"PP"},{"deputyID":1548,"vote":1,"party":"PRB"},{"deputyID":636,"vote":3,"party":"PMDB"},{"deputyID":1136,"vote":3,"party":"PSDB"},{"deputyID":638,"vote":1,"party":"PSOL"},{"deputyID":1949,"vote":3,"party":"PSD"},{"deputyID":220,"vote":0,"party":"PTB"},{"deputyID":1037,"vote":3,"party":"PT"},{"deputyID":1740,"vote":1,"party":"PR"},{"deputyID":1516,"vote":3,"party":"PSD"},{"deputyID":470,"vote":1,"party":"PR"},{"deputyID":1747,"vote":0,"party":"PDT"},{"deputyID":1749,"vote":3,"party":"PSD"},{"deputyID":1750,"vote":3,"party":"PMDB"},{"deputyID":1257,"vote":3,"party":"PMDB"},{"deputyID":1168,"vote":1,"party":"PTB"},{"deputyID":816,"vote":3,"party":"PMDB"},{"deputyID":1756,"vote":3,"party":"PV"},{"deputyID":1761,"vote":2,"party":"PSD"},{"deputyID":1945,"vote":3,"party":"PT"},{"deputyID":233,"vote":0,"party":"PPS"},{"deputyID":686,"vote":3,"party":"PMDB"},{"deputyID":1782,"vote":2,"party":"PSB"},{"deputyID":1783,"vote":3,"party":"PT"},{"deputyID":1562,"vote":3,"party":"DEM"},{"deputyID":2229,"vote":3,"party":"PSD"},{"deputyID":370,"vote":0,"party":"PPS"},{"deputyID":2001,"vote":3,"party":"PT"},{"deputyID":1789,"vote":1,"party":"PT"},{"deputyID":41,"vote":2,"party":"PMDB"},{"deputyID":1153,"vote":3,"party":"PMDB"},{"deputyID":1396,"vote":3,"party":"DEM"},{"deputyID":1432,"vote":3,"party":"PMDB"}]}]}