{
    "deputyNodes": [
        {
            "deputyID": 5,
            "scatterplot": [
                -0.6506,
                -0.2516
            ],
            "party": "PMDB"
        },
        {
            "deputyID": 12,
            "scatterplot": [
                -0.8496,
                -0.02797
            ],
            "party": "PDT"
        },
        {
            "deputyID": 18,
            "scatterplot": [
                -0.8368,
                0.005799
            ],
            "party": "PT"
        },
        {
            "deputyID": 20,
            "scatterplot": [
                -0.6123,
                -0.05052
            ],
            "party": "PMDB"
        },
        {
            "deputyID": 28,
            "scatterplot": [
                -0.6,
                -0.06449
            ],
            "party": "PR"
        },
        {
            "deputyID": 41,
            "scatterplot": [
                -0.6067,
                -0.05158
            ],
            "party": "PMDB"
        },
        {
            "deputyID": 48,
            "scatterplot": [
                -0.7692,
                -0.1288
            ],
            "party": "PP"
        },
        {
            "deputyID": 63,
            "scatterplot": [
                -0.3609,
                -0.07163
            ],
            "party": "PMDB"
        },
        {
            "deputyID": 74,
            "scatterplot": [
                0.2015,
                -0.5333
            ],
            "party": "DEM"
        },
        {
            "deputyID": 78,
            "scatterplot": [
                -0.661,
                0.1375
            ],
            "party": "PCdoB"
        },
        {
            "deputyID": 80,
            "scatterplot": [
                0.1934,
                -0.5438
            ],
            "party": "DEM"
        },
        {
            "deputyID": 85,
            "scatterplot": [
                -0.6511,
                0.001021
            ],
            "party": "PMDB"
        },
        {
            "deputyID": 88,
            "scatterplot": [
                -0.2163,
                -0.2029
            ],
            "party": "DEM"
        },
        {
            "deputyID": 96,
            "scatterplot": [
                0.2145,
                -0.6815
            ],
            "party": "DEM"
        },
        {
            "deputyID": 101,
            "scatterplot": [
                0.2049,
                -0.8303
            ],
            "party": "DEM"
        },
        {
            "deputyID": 102,
            "scatterplot": [
                0.234,
                -0.7259
            ],
            "party": "DEM"
        },
        {
            "deputyID": 110,
            "scatterplot": [
                -0.6912,
                0.08328
            ],
            "party": "PMN"
        },
        {
            "deputyID": 114,
            "scatterplot": [
                -0.01333,
                -0.1996
            ],
            "party": "DEM"
        },
        {
            "deputyID": 116,
            "scatterplot": [
                -0.6317,
                0.0309
            ],
            "party": "PMDB"
        },
        {
            "deputyID": 118,
            "scatterplot": [
                0.1299,
                -0.8075
            ],
            "party": "PPS"
        },
        {
            "deputyID": 123,
            "scatterplot": [
                -0.4165,
                -0.05015
            ],
            "party": "DEM"
        },
        {
            "deputyID": 141,
            "scatterplot": [
                -0.4434,
                -0.4531
            ],
            "party": "PMDB"
        },
        {
            "deputyID": 147,
            "scatterplot": [
                -0.09016,
                -0.6258
            ],
            "party": "PP"
        },
        {
            "deputyID": 151,
            "scatterplot": [
                -0.5014,
                -0.005258
            ],
            "party": "PMDB"
        },
        {
            "deputyID": 157,
            "scatterplot": [
                -0.8577,
                -0.04123
            ],
            "party": "PP"
        },
        {
            "deputyID": 159,
            "scatterplot": [
                -0.8647,
                -0.06728
            ],
            "party": "PDT"
        },
        {
            "deputyID": 175,
            "scatterplot": [
                0.1528,
                -0.5059
            ],
            "party": "DEM"
        },
        {
            "deputyID": 177,
            "scatterplot": [
                -0.9277,
                0.02461
            ],
            "party": "PT"
        },
        {
            "deputyID": 183,
            "scatterplot": [
                -0.7858,
                -0.1753
            ],
            "party": "PTB"
        },
        {
            "deputyID": 187,
            "scatterplot": [
                -0.6745,
                -0.1066
            ],
            "party": "PR"
        },
        {
            "deputyID": 193,
            "scatterplot": [
                -0.3294,
                0.0227
            ],
            "party": "PR"
        },
        {
            "deputyID": 194,
            "scatterplot": [
                0.3932,
                -0.6509
            ],
            "party": "PPS"
        },
        {
            "deputyID": 196,
            "scatterplot": [
                -0.8001,
                -0.3261
            ],
            "party": "PR"
        },
        {
            "deputyID": 199,
            "scatterplot": [
                0.1335,
                -0.4281
            ],
            "party": "DEM"
        },
        {
            "deputyID": 218,
            "scatterplot": [
                0.2065,
                -0.7077
            ],
            "party": "PSDB"
        },
        {
            "deputyID": 232,
            "scatterplot": [
                -0.7559,
                0.004174
            ],
            "party": "PT"
        },
        {
            "deputyID": 269,
            "scatterplot": [
                -0.6516,
                -0.2082
            ],
            "party": "PMDB"
        },
        {
            "deputyID": 274,
            "scatterplot": [
                -0.6897,
                -0.01743
            ],
            "party": "PMDB"
        },
        {
            "deputyID": 290,
            "scatterplot": [
                -0.3156,
                -0.0921
            ],
            "party": "PMDB"
        },
        {
            "deputyID": 292,
            "scatterplot": [
                -0.8233,
                -0.0258
            ],
            "party": "PT"
        },
        {
            "deputyID": 293,
            "scatterplot": [
                -0.6823,
                -0.166
            ],
            "party": "PR"
        },
        {
            "deputyID": 301,
            "scatterplot": [
                -0.8981,
                -0.05716
            ],
            "party": "PP"
        },
        {
            "deputyID": 305,
            "scatterplot": [
                -0.8974,
                -0.00994
            ],
            "party": "PTB"
        },
        {
            "deputyID": 309,
            "scatterplot": [
                0.1711,
                -0.7648
            ],
            "party": "DEM"
        },
        {
            "deputyID": 314,
            "scatterplot": [
                -0.7014,
                -0.02298
            ],
            "party": "PTB"
        },
        {
            "deputyID": 321,
            "scatterplot": [
                0.1987,
                -1.013
            ],
            "party": "PSDB"
        },
        {
            "deputyID": 322,
            "scatterplot": [
                -0.7739,
                0.03306
            ],
            "party": "PP"
        },
        {
            "deputyID": 324,
            "scatterplot": [
                -0.601,
                -0.2222
            ],
            "party": "PR"
        },
        {
            "deputyID": 327,
            "scatterplot": [
                -0.3989,
                -0.05279
            ],
            "party": "PP"
        },
        {
            "deputyID": 331,
            "scatterplot": [
                -0.7208,
                0.07416
            ],
            "party": "PDT"
        },
        {
            "deputyID": 339,
            "scatterplot": [
                0.09307,
                -0.5336
            ],
            "party": "PSDB"
        },
        {
            "deputyID": 345,
            "scatterplot": [
                -0.558,
                -0.06986
            ],
            "party": "PR"
        },
        {
            "deputyID": 348,
            "scatterplot": [
                -0.8429,
                0.007386
            ],
            "party": "PT"
        },
        {
            "deputyID": 351,
            "scatterplot": [
                -0.8032,
                -0.2513
            ],
            "party": "PMDB"
        },
        {
            "deputyID": 352,
            "scatterplot": [
                -0.8393,
                -0.07887
            ],
            "party": "PP"
        },
        {
            "deputyID": 353,
            "scatterplot": [
                -0.6513,
                -0.0209
            ],
            "party": "PSC"
        },
        {
            "deputyID": 355,
            "scatterplot": [
                -0.4026,
                0.01063
            ],
            "party": "PMDB"
        },
        {
            "deputyID": 366,
            "scatterplot": [
                -0.5945,
                0.02217
            ],
            "party": "PMDB"
        },
        {
            "deputyID": 374,
            "scatterplot": [
                -0.7216,
                0.07899
            ],
            "party": "PCdoB"
        },
        {
            "deputyID": 377,
            "scatterplot": [
                0,
                0
            ],
            "party": "PT"
        },
        {
            "deputyID": 378,
            "scatterplot": [
                0.3545,
                -0.4144
            ],
            "party": "PTB"
        },
        {
            "deputyID": 381,
            "scatterplot": [
                0.05237,
                -0.4534
            ],
            "party": "PV"
        },
        {
            "deputyID": 383,
            "scatterplot": [
                -0.6513,
                -0.08913
            ],
            "party": "PMDB"
        },
        {
            "deputyID": 389,
            "scatterplot": [
                0.01213,
                -0.5382
            ],
            "party": "PSOL"
        },
        {
            "deputyID": 398,
            "scatterplot": [
                -0.8124,
                -0.1187
            ],
            "party": "PTB"
        },
        {
            "deputyID": 400,
            "scatterplot": [
                0.1894,
                -0.9065
            ],
            "party": "PSDB"
        },
        {
            "deputyID": 416,
            "scatterplot": [
                0.1173,
                -0.6031
            ],
            "party": "DEM"
        },
        {
            "deputyID": 417,
            "scatterplot": [
                -0.7561,
                -0.1473
            ],
            "party": "PDT"
        },
        {
            "deputyID": 419,
            "scatterplot": [
                -0.673,
                -0.1722
            ],
            "party": "PTB"
        },
        {
            "deputyID": 424,
            "scatterplot": [
                -0.9327,
                -0.01892
            ],
            "party": "PT"
        },
        {
            "deputyID": 427,
            "scatterplot": [
                -0.6162,
                0.009891
            ],
            "party": "PR"
        },
        {
            "deputyID": 432,
            "scatterplot": [
                -0.6111,
                -0.2157
            ],
            "party": "PMDB"
        },
        {
            "deputyID": 434,
            "scatterplot": [
                0.1904,
                -0.874
            ],
            "party": "PSDB"
        },
        {
            "deputyID": 436,
            "scatterplot": [
                -0.7929,
                -0.1608
            ],
            "party": "PP"
        },
        {
            "deputyID": 442,
            "scatterplot": [
                -0.894,
                -0.0648
            ],
            "party": "PP"
        },
        {
            "deputyID": 446,
            "scatterplot": [
                -0.5021,
                -0.09319
            ],
            "party": "PMDB"
        },
        {
            "deputyID": 449,
            "scatterplot": [
                -0.589,
                -0.03302
            ],
            "party": "PMDB"
        },
        {
            "deputyID": 450,
            "scatterplot": [
                0.1328,
                -0.2336
            ],
            "party": "DEM"
        },
        {
            "deputyID": 468,
            "scatterplot": [
                0.2133,
                -0.9774
            ],
            "party": "PSDB"
        },
        {
            "deputyID": 478,
            "scatterplot": [
                0.05703,
                -0.6169
            ],
            "party": "PSDB"
        },
        {
            "deputyID": 482,
            "scatterplot": [
                -0.6964,
                -0.08692
            ],
            "party": "PR"
        },
        {
            "deputyID": 489,
            "scatterplot": [
                0.2455,
                -0.8512
            ],
            "party": "DEM"
        },
        {
            "deputyID": 492,
            "scatterplot": [
                -0.7589,
                -0.1764
            ],
            "party": "PR"
        },
        {
            "deputyID": 495,
            "scatterplot": [
                -0.5925,
                -0.09324
            ],
            "party": "PP"
        },
        {
            "deputyID": 498,
            "scatterplot": [
                -0.4385,
                -0.2936
            ],
            "party": "DEM"
        },
        {
            "deputyID": 500,
            "scatterplot": [
                -0.3333,
                0.09177
            ],
            "party": "DEM"
        },
        {
            "deputyID": 501,
            "scatterplot": [
                -0.6181,
                0.01597
            ],
            "party": "PMDB"
        },
        {
            "deputyID": 504,
            "scatterplot": [
                -0.7071,
                0.09675
            ],
            "party": "PT"
        },
        {
            "deputyID": 510,
            "scatterplot": [
                -0.8257,
                0.1094
            ],
            "party": "PT"
        },
        {
            "deputyID": 516,
            "scatterplot": [
                0.1751,
                -0.6357
            ],
            "party": "DEM"
        },
        {
            "deputyID": 524,
            "scatterplot": [
                -0.524,
                -0.07308
            ],
            "party": "PR"
        },
        {
            "deputyID": 532,
            "scatterplot": [
                -0.6722,
                -0.1012
            ],
            "party": "PMDB"
        },
        {
            "deputyID": 533,
            "scatterplot": [
                -0.5089,
                0.109
            ],
            "party": "PSB"
        },
        {
            "deputyID": 536,
            "scatterplot": [
                -0.5101,
                0.0474
            ],
            "party": "PSB"
        },
        {
            "deputyID": 540,
            "scatterplot": [
                -0.8234,
                0.113
            ],
            "party": "PDT"
        },
        {
            "deputyID": 541,
            "scatterplot": [
                -0.7949,
                -0.08425
            ],
            "party": "PTB"
        },
        {
            "deputyID": 548,
            "scatterplot": [
                -0.8084,
                -0.03875
            ],
            "party": "PDT"
        },
        {
            "deputyID": 550,
            "scatterplot": [
                -0.7238,
                -0.06721
            ],
            "party": "PMDB"
        },
        {
            "deputyID": 552,
            "scatterplot": [
                -0.7936,
                -0.1341
            ],
            "party": "PR"
        },
        {
            "deputyID": 553,
            "scatterplot": [
                0.2261,
                -0.9342
            ],
            "party": "PSDB"
        },
        {
            "deputyID": 565,
            "scatterplot": [
                0.2587,
                -0.9883
            ],
            "party": "PSDB"
        },
        {
            "deputyID": 573,
            "scatterplot": [
                0.1766,
                -0.7104
            ],
            "party": "PSDB"
        },
        {
            "deputyID": 581,
            "scatterplot": [
                -0.4659,
                -0.03528
            ],
            "party": "PMDB"
        },
        {
            "deputyID": 583,
            "scatterplot": [
                -0.697,
                -0.4675
            ],
            "party": "PSC"
        },
        {
            "deputyID": 586,
            "scatterplot": [
                -0.4831,
                -0.1462
            ],
            "party": "PP"
        },
        {
            "deputyID": 588,
            "scatterplot": [
                -0.4458,
                -0.03308
            ],
            "party": "PP"
        },
        {
            "deputyID": 595,
            "scatterplot": [
                -0.4991,
                0.1124
            ],
            "party": "PMDB"
        },
        {
            "deputyID": 602,
            "scatterplot": [
                -0.4217,
                0.04646
            ],
            "party": "PP"
        },
        {
            "deputyID": 603,
            "scatterplot": [
                0.1943,
                -0.587
            ],
            "party": "DEM"
        },
        {
            "deputyID": 611,
            "scatterplot": [
                -0.6164,
                0.00258
            ],
            "party": "PMDB"
        },
        {
            "deputyID": 613,
            "scatterplot": [
                -0.7242,
                0.1079
            ],
            "party": "PTB"
        },
        {
            "deputyID": 619,
            "scatterplot": [
                0.1252,
                -0.689
            ],
            "party": "PSDB"
        },
        {
            "deputyID": 621,
            "scatterplot": [
                -0.683,
                -0.08216
            ],
            "party": "PTB"
        },
        {
            "deputyID": 623,
            "scatterplot": [
                -0.5991,
                0.001033
            ],
            "party": "PR"
        },
        {
            "deputyID": 634,
            "scatterplot": [
                -0.7044,
                -0.08592
            ],
            "party": "PMDB"
        },
        {
            "deputyID": 635,
            "scatterplot": [
                0.04698,
                -0.549
            ],
            "party": "DEM"
        },
        {
            "deputyID": 640,
            "scatterplot": [
                -0.4154,
                -0.1649
            ],
            "party": "PP"
        },
        {
            "deputyID": 648,
            "scatterplot": [
                -0.7612,
                -0.1236
            ],
            "party": "PMDB"
        },
        {
            "deputyID": 652,
            "scatterplot": [
                -0.8087,
                0.04106
            ],
            "party": "PCdoB"
        },
        {
            "deputyID": 653,
            "scatterplot": [
                -0.8757,
                -0.1413
            ],
            "party": "PMDB"
        },
        {
            "deputyID": 657,
            "scatterplot": [
                0.1455,
                -0.8437
            ],
            "party": "PSDB"
        },
        {
            "deputyID": 659,
            "scatterplot": [
                0.2289,
                -0.9174
            ],
            "party": "PSDB"
        },
        {
            "deputyID": 661,
            "scatterplot": [
                -0.6206,
                0.04865
            ],
            "party": "PSC"
        },
        {
            "deputyID": 662,
            "scatterplot": [
                -0.8548,
                -0.02177
            ],
            "party": "PCdoB"
        },
        {
            "deputyID": 670,
            "scatterplot": [
                -0.8787,
                -0.003915
            ],
            "party": "PT"
        },
        {
            "deputyID": 675,
            "scatterplot": [
                0.1532,
                -0.5091
            ],
            "party": "DEM"
        },
        {
            "deputyID": 679,
            "scatterplot": [
                -0.6312,
                0.02175
            ],
            "party": "PMDB"
        },
        {
            "deputyID": 680,
            "scatterplot": [
                -0.5563,
                -0.1324
            ],
            "party": "PR"
        },
        {
            "deputyID": 681,
            "scatterplot": [
                -0.3652,
                -0.3116
            ],
            "party": "PSDB"
        },
        {
            "deputyID": 683,
            "scatterplot": [
                -0.9051,
                0.0391
            ],
            "party": "PSB"
        },
        {
            "deputyID": 684,
            "scatterplot": [
                -0.8437,
                -0.1187
            ],
            "party": "PMDB"
        },
        {
            "deputyID": 692,
            "scatterplot": [
                -0.595,
                0.01786
            ],
            "party": "PSB"
        },
        {
            "deputyID": 693,
            "scatterplot": [
                -0.2656,
                -0.1576
            ],
            "party": "PTB"
        },
        {
            "deputyID": 699,
            "scatterplot": [
                -0.8311,
                0.03302
            ],
            "party": "PT"
        },
        {
            "deputyID": 700,
            "scatterplot": [
                -0.5411,
                0.1026
            ],
            "party": "PSB"
        },
        {
            "deputyID": 711,
            "scatterplot": [
                0.1941,
                -1.033
            ],
            "party": "PSDB"
        },
        {
            "deputyID": 712,
            "scatterplot": [
                -0.7969,
                -0.07481
            ],
            "party": "PT"
        },
        {
            "deputyID": 715,
            "scatterplot": [
                0.1468,
                -0.6968
            ],
            "party": "DEM"
        },
        {
            "deputyID": 720,
            "scatterplot": [
                -0.8387,
                -0.01438
            ],
            "party": "PT"
        },
        {
            "deputyID": 722,
            "scatterplot": [
                -0.8458,
                -0.05952
            ],
            "party": "PR"
        },
        {
            "deputyID": 723,
            "scatterplot": [
                -0.8629,
                0.01825
            ],
            "party": "PT"
        },
        {
            "deputyID": 725,
            "scatterplot": [
                0.1672,
                -0.739
            ],
            "party": "PSDB"
        },
        {
            "deputyID": 741,
            "scatterplot": [
                -0.8094,
                0.02627
            ],
            "party": "PT"
        },
        {
            "deputyID": 744,
            "scatterplot": [
                0.1711,
                -0.5667
            ],
            "party": "DEM"
        },
        {
            "deputyID": 750,
            "scatterplot": [
                -0.7834,
                0.04563
            ],
            "party": "PT"
        },
        {
            "deputyID": 759,
            "scatterplot": [
                0.1333,
                -0.8765
            ],
            "party": "PSDB"
        },
        {
            "deputyID": 760,
            "scatterplot": [
                -0.2526,
                -0.4782
            ],
            "party": "PSB"
        },
        {
            "deputyID": 762,
            "scatterplot": [
                -0.7997,
                0.06199
            ],
            "party": "PR"
        },
        {
            "deputyID": 767,
            "scatterplot": [
                -0.528,
                0.009455
            ],
            "party": "PT"
        },
        {
            "deputyID": 782,
            "scatterplot": [
                -0.681,
                -0.1992
            ],
            "party": "PMDB"
        },
        {
            "deputyID": 783,
            "scatterplot": [
                -0.622,
                -0.05778
            ],
            "party": "PR"
        },
        {
            "deputyID": 784,
            "scatterplot": [
                -0.4807,
                0.03476
            ],
            "party": "PT"
        },
        {
            "deputyID": 785,
            "scatterplot": [
                0.1592,
                -0.8988
            ],
            "party": "PSDB"
        },
        {
            "deputyID": 789,
            "scatterplot": [
                -0.6858,
                -0.1208
            ],
            "party": "PMDB"
        },
        {
            "deputyID": 794,
            "scatterplot": [
                -0.83,
                -0.03313
            ],
            "party": "PT"
        },
        {
            "deputyID": 795,
            "scatterplot": [
                0.2102,
                -0.946
            ],
            "party": "PPS"
        },
        {
            "deputyID": 796,
            "scatterplot": [
                0.1792,
                -0.5568
            ],
            "party": "PSDB"
        },
        {
            "deputyID": 800,
            "scatterplot": [
                -0.4697,
                -0.1478
            ],
            "party": "PMDB"
        },
        {
            "deputyID": 802,
            "scatterplot": [
                -0.8558,
                -0.01052
            ],
            "party": "PT"
        },
        {
            "deputyID": 803,
            "scatterplot": [
                -0.499,
                -0.4703
            ],
            "party": "PP"
        },
        {
            "deputyID": 806,
            "scatterplot": [
                -0.6263,
                0.01834
            ],
            "party": "PDT"
        },
        {
            "deputyID": 814,
            "scatterplot": [
                0.1381,
                -0.4058
            ],
            "party": "DEM"
        },
        {
            "deputyID": 818,
            "scatterplot": [
                -0.6251,
                -0.1402
            ],
            "party": "PMDB"
        },
        {
            "deputyID": 819,
            "scatterplot": [
                -0.3639,
                -0.214
            ],
            "party": "PMDB"
        },
        {
            "deputyID": 820,
            "scatterplot": [
                -0.6937,
                -0.1153
            ],
            "party": "PP"
        },
        {
            "deputyID": 821,
            "scatterplot": [
                -0.7463,
                -0.2127
            ],
            "party": "PMDB"
        },
        {
            "deputyID": 830,
            "scatterplot": [
                0.1986,
                -0.9381
            ],
            "party": "PSDB"
        },
        {
            "deputyID": 833,
            "scatterplot": [
                -0.8757,
                -0.07664
            ],
            "party": "PT"
        },
        {
            "deputyID": 848,
            "scatterplot": [
                -0.6061,
                -0.07773
            ],
            "party": "PMDB"
        },
        {
            "deputyID": 853,
            "scatterplot": [
                -0.9002,
                -0.02711
            ],
            "party": "PSB"
        },
        {
            "deputyID": 855,
            "scatterplot": [
                -0.4356,
                -0.1297
            ],
            "party": "PMDB"
        },
        {
            "deputyID": 856,
            "scatterplot": [
                -0.8199,
                -0.146
            ],
            "party": "PMDB"
        },
        {
            "deputyID": 857,
            "scatterplot": [
                -0.9046,
                -0.124
            ],
            "party": "PMDB"
        },
        {
            "deputyID": 858,
            "scatterplot": [
                0.3048,
                -0.7992
            ],
            "party": "DEM"
        },
        {
            "deputyID": 860,
            "scatterplot": [
                -0.8978,
                -0.09353
            ],
            "party": "PTB"
        },
        {
            "deputyID": 861,
            "scatterplot": [
                -0.5804,
                -0.0829
            ],
            "party": "PV"
        },
        {
            "deputyID": 862,
            "scatterplot": [
                0.1184,
                -0.7518
            ],
            "party": "PSDB"
        },
        {
            "deputyID": 863,
            "scatterplot": [
                -0.7565,
                -0.0693
            ],
            "party": "PMDB"
        },
        {
            "deputyID": 865,
            "scatterplot": [
                -0.5329,
                -0.2275
            ],
            "party": "PSB"
        },
        {
            "deputyID": 867,
            "scatterplot": [
                0.1301,
                -0.7396
            ],
            "party": "PSDB"
        },
        {
            "deputyID": 869,
            "scatterplot": [
                -0.7911,
                0.06304
            ],
            "party": "PT"
        },
        {
            "deputyID": 870,
            "scatterplot": [
                -0.685,
                -0.2266
            ],
            "party": "PP"
        },
        {
            "deputyID": 871,
            "scatterplot": [
                -0.6524,
                -0.04701
            ],
            "party": "PMDB"
        },
        {
            "deputyID": 873,
            "scatterplot": [
                0.2211,
                -0.7619
            ],
            "party": "DEM"
        },
        {
            "deputyID": 874,
            "scatterplot": [
                -0.7961,
                -0.198
            ],
            "party": "PSC"
        },
        {
            "deputyID": 875,
            "scatterplot": [
                -0.5057,
                -0.1969
            ],
            "party": "PTB"
        },
        {
            "deputyID": 877,
            "scatterplot": [
                -0.8181,
                -0.04109
            ],
            "party": "PT"
        },
        {
            "deputyID": 878,
            "scatterplot": [
                -0.7516,
                -0.0003625
            ],
            "party": "PSB"
        },
        {
            "deputyID": 879,
            "scatterplot": [
                -0.6835,
                -0.06967
            ],
            "party": "PMDB"
        },
        {
            "deputyID": 880,
            "scatterplot": [
                -0.8234,
                -0.002004
            ],
            "party": "PT"
        },
        {
            "deputyID": 883,
            "scatterplot": [
                0.2305,
                -0.8593
            ],
            "party": "PSDB"
        },
        {
            "deputyID": 885,
            "scatterplot": [
                -0.6659,
                0.03927
            ],
            "party": "PT"
        },
        {
            "deputyID": 893,
            "scatterplot": [
                -0.6858,
                -0.04125
            ],
            "party": "PT"
        },
        {
            "deputyID": 895,
            "scatterplot": [
                -0.7411,
                0.06107
            ],
            "party": "PCdoB"
        },
        {
            "deputyID": 898,
            "scatterplot": [
                -0.7048,
                0.08223
            ],
            "party": "PR"
        },
        {
            "deputyID": 900,
            "scatterplot": [
                -0.609,
                -0.1221
            ],
            "party": "PP"
        },
        {
            "deputyID": 904,
            "scatterplot": [
                0.1441,
                -0.4677
            ],
            "party": "DEM"
        },
        {
            "deputyID": 905,
            "scatterplot": [
                -0.7641,
                0.09124
            ],
            "party": "PCdoB"
        },
        {
            "deputyID": 906,
            "scatterplot": [
                0.2518,
                -0.7282
            ],
            "party": "DEM"
        },
        {
            "deputyID": 907,
            "scatterplot": [
                -0.6711,
                0.08967
            ],
            "party": "PT"
        },
        {
            "deputyID": 908,
            "scatterplot": [
                -0.8035,
                0.03829
            ],
            "party": "PMDB"
        },
        {
            "deputyID": 909,
            "scatterplot": [
                -0.7835,
                0.03968
            ],
            "party": "PCdoB"
        },
        {
            "deputyID": 910,
            "scatterplot": [
                -0.6101,
                -0.1258
            ],
            "party": "PV"
        },
        {
            "deputyID": 911,
            "scatterplot": [
                0.2435,
                -0.7902
            ],
            "party": "DEM"
        },
        {
            "deputyID": 912,
            "scatterplot": [
                0.116,
                -0.5953
            ],
            "party": "DEM"
        },
        {
            "deputyID": 913,
            "scatterplot": [
                -0.9671,
                -0.04875
            ],
            "party": "PT"
        },
        {
            "deputyID": 914,
            "scatterplot": [
                -0.6947,
                -0.01509
            ],
            "party": "PR"
        },
        {
            "deputyID": 916,
            "scatterplot": [
                0.2004,
                -0.7999
            ],
            "party": "DEM"
        },
        {
            "deputyID": 917,
            "scatterplot": [
                -0.6623,
                -0.0331
            ],
            "party": "PMDB"
        },
        {
            "deputyID": 920,
            "scatterplot": [
                -0.738,
                -0.04917
            ],
            "party": "PT"
        },
        {
            "deputyID": 925,
            "scatterplot": [
                -0.7067,
                -0.0447
            ],
            "party": "PTB"
        },
        {
            "deputyID": 926,
            "scatterplot": [
                -0.9371,
                -0.03588
            ],
            "party": "PDT"
        },
        {
            "deputyID": 928,
            "scatterplot": [
                -0.4416,
                -0.06173
            ],
            "party": "PR"
        },
        {
            "deputyID": 930,
            "scatterplot": [
                0.1109,
                -0.6484
            ],
            "party": "PSDB"
        },
        {
            "deputyID": 931,
            "scatterplot": [
                0.1286,
                -0.7326
            ],
            "party": "PSDB"
        },
        {
            "deputyID": 932,
            "scatterplot": [
                -0.7185,
                -0.1098
            ],
            "party": "PMDB"
        },
        {
            "deputyID": 933,
            "scatterplot": [
                0.2436,
                -0.8858
            ],
            "party": "PSDB"
        },
        {
            "deputyID": 935,
            "scatterplot": [
                -0.688,
                0.1235
            ],
            "party": "PT"
        },
        {
            "deputyID": 936,
            "scatterplot": [
                -0.7254,
                -0.03806
            ],
            "party": "PP"
        },
        {
            "deputyID": 942,
            "scatterplot": [
                -0.5954,
                0.03335
            ],
            "party": "PTC"
        },
        {
            "deputyID": 945,
            "scatterplot": [
                -0.2264,
                -0.5536
            ],
            "party": "PPS"
        },
        {
            "deputyID": 949,
            "scatterplot": [
                -0.5628,
                -0.08034
            ],
            "party": "PR"
        },
        {
            "deputyID": 951,
            "scatterplot": [
                -0.6762,
                0.1498
            ],
            "party": "PT"
        },
        {
            "deputyID": 952,
            "scatterplot": [
                -0.6901,
                -0.03019
            ],
            "party": "PDT"
        },
        {
            "deputyID": 953,
            "scatterplot": [
                -0.88,
                -0.01203
            ],
            "party": "PT"
        },
        {
            "deputyID": 954,
            "scatterplot": [
                -0.8301,
                0.09351
            ],
            "party": "PT"
        },
        {
            "deputyID": 955,
            "scatterplot": [
                -0.7943,
                -0.05019
            ],
            "party": "PT"
        },
        {
            "deputyID": 956,
            "scatterplot": [
                -0.5297,
                -0.4385
            ],
            "party": "PMDB"
        },
        {
            "deputyID": 958,
            "scatterplot": [
                -0.8067,
                0.08139
            ],
            "party": "PT"
        },
        {
            "deputyID": 959,
            "scatterplot": [
                0.1589,
                -0.5149
            ],
            "party": "PSDB"
        },
        {
            "deputyID": 961,
            "scatterplot": [
                -0.5372,
                -0.04321
            ],
            "party": "PMDB"
        },
        {
            "deputyID": 962,
            "scatterplot": [
                -0.7325,
                0.02608
            ],
            "party": "PT"
        },
        {
            "deputyID": 964,
            "scatterplot": [
                -0.7699,
                0.03267
            ],
            "party": "PMDB"
        },
        {
            "deputyID": 967,
            "scatterplot": [
                -0.8974,
                -0.02053
            ],
            "party": "PT"
        },
        {
            "deputyID": 968,
            "scatterplot": [
                -0.7308,
                -0.1263
            ],
            "party": "PR"
        },
        {
            "deputyID": 969,
            "scatterplot": [
                -0.7687,
                0.009971
            ],
            "party": "PMDB"
        },
        {
            "deputyID": 971,
            "scatterplot": [
                -0.6808,
                0.02849
            ],
            "party": "PDT"
        },
        {
            "deputyID": 972,
            "scatterplot": [
                0.1215,
                -0.4696
            ],
            "party": "PPS"
        },
        {
            "deputyID": 976,
            "scatterplot": [
                0.1173,
                -0.661
            ],
            "party": "PPS"
        },
        {
            "deputyID": 980,
            "scatterplot": [
                -0.4485,
                -0.1488
            ],
            "party": "PMDB"
        },
        {
            "deputyID": 982,
            "scatterplot": [
                0.02564,
                -0.578
            ],
            "party": "PSOL"
        },
        {
            "deputyID": 983,
            "scatterplot": [
                -0.6526,
                0.001011
            ],
            "party": "PSC"
        },
        {
            "deputyID": 984,
            "scatterplot": [
                -0.764,
                0.06352
            ],
            "party": "PT"
        },
        {
            "deputyID": 987,
            "scatterplot": [
                -0.7264,
                -0.03532
            ],
            "party": "PMDB"
        },
        {
            "deputyID": 999,
            "scatterplot": [
                -0.6387,
                -0.04048
            ],
            "party": "PMDB"
        },
        {
            "deputyID": 1000,
            "scatterplot": [
                -0.7949,
                0.004126
            ],
            "party": "PT"
        },
        {
            "deputyID": 1001,
            "scatterplot": [
                -0.5941,
                -0.02532
            ],
            "party": "PT"
        },
        {
            "deputyID": 1003,
            "scatterplot": [
                0.2137,
                -0.9583
            ],
            "party": "PSDB"
        },
        {
            "deputyID": 1006,
            "scatterplot": [
                -0.7673,
                -0.2075
            ],
            "party": "PV"
        },
        {
            "deputyID": 1007,
            "scatterplot": [
                -0.1991,
                -0.09256
            ],
            "party": "PR"
        },
        {
            "deputyID": 1013,
            "scatterplot": [
                -0.6419,
                0.09822
            ],
            "party": "PT"
        },
        {
            "deputyID": 1014,
            "scatterplot": [
                -0.8138,
                0.04173
            ],
            "party": "PT"
        },
        {
            "deputyID": 1017,
            "scatterplot": [
                -0.7858,
                0.06331
            ],
            "party": "PT"
        },
        {
            "deputyID": 1020,
            "scatterplot": [
                -0.6604,
                -0.209
            ],
            "party": "PSB"
        },
        {
            "deputyID": 1028,
            "scatterplot": [
                0.04166,
                -0.4534
            ],
            "party": "PSOL"
        },
        {
            "deputyID": 1029,
            "scatterplot": [
                -0.6738,
                0.06125
            ],
            "party": "PT"
        },
        {
            "deputyID": 1031,
            "scatterplot": [
                -0.6652,
                -0.1154
            ],
            "party": "PT"
        },
        {
            "deputyID": 1037,
            "scatterplot": [
                -0.8327,
                -0.0293
            ],
            "party": "PT"
        },
        {
            "deputyID": 1038,
            "scatterplot": [
                -0.859,
                -0.2005
            ],
            "party": "PP"
        },
        {
            "deputyID": 1041,
            "scatterplot": [
                -0.7809,
                -0.0006398
            ],
            "party": "PMDB"
        },
        {
            "deputyID": 1043,
            "scatterplot": [
                0.1457,
                -0.4984
            ],
            "party": "DEM"
        },
        {
            "deputyID": 1046,
            "scatterplot": [
                0.1556,
                -0.6529
            ],
            "party": "PSDB"
        },
        {
            "deputyID": 1047,
            "scatterplot": [
                0.1624,
                -0.8018
            ],
            "party": "PPS"
        },
        {
            "deputyID": 1056,
            "scatterplot": [
                -0.8402,
                -0.1299
            ],
            "party": "PMDB"
        },
        {
            "deputyID": 1058,
            "scatterplot": [
                -0.884,
                0.05975
            ],
            "party": "PT"
        },
        {
            "deputyID": 1063,
            "scatterplot": [
                -0.8421,
                -0.08682
            ],
            "party": "PMDB"
        },
        {
            "deputyID": 1064,
            "scatterplot": [
                -0.8812,
                0.04602
            ],
            "party": "PT"
        },
        {
            "deputyID": 1065,
            "scatterplot": [
                -0.6348,
                -0.07533
            ],
            "party": "PDT"
        },
        {
            "deputyID": 1078,
            "scatterplot": [
                -0.6916,
                -0.3121
            ],
            "party": "PP"
        },
        {
            "deputyID": 1082,
            "scatterplot": [
                -0.629,
                -0.1458
            ],
            "party": "PP"
        },
        {
            "deputyID": 1084,
            "scatterplot": [
                -0.6439,
                0.006383
            ],
            "party": "PMDB"
        },
        {
            "deputyID": 1088,
            "scatterplot": [
                -0.4389,
                -0.19
            ],
            "party": "PSB"
        },
        {
            "deputyID": 1089,
            "scatterplot": [
                -0.6403,
                -0.01948
            ],
            "party": "PT"
        },
        {
            "deputyID": 1092,
            "scatterplot": [
                -0.655,
                -0.1702
            ],
            "party": "PR"
        },
        {
            "deputyID": 1093,
            "scatterplot": [
                -0.6536,
                -0.02677
            ],
            "party": "PSC"
        },
        {
            "deputyID": 1095,
            "scatterplot": [
                -0.3732,
                -0.01503
            ],
            "party": "PSB"
        },
        {
            "deputyID": 1096,
            "scatterplot": [
                0.1707,
                -0.5653
            ],
            "party": "DEM"
        },
        {
            "deputyID": 1097,
            "scatterplot": [
                -0.5401,
                0.01386
            ],
            "party": "PR"
        },
        {
            "deputyID": 1143,
            "scatterplot": [
                -0.5358,
                -0.1882
            ],
            "party": "PP"
        },
        {
            "deputyID": 1160,
            "scatterplot": [
                -0.6357,
                -0.1212
            ],
            "party": "PMDB"
        },
        {
            "deputyID": 1209,
            "scatterplot": [
                -0.8187,
                -0.05128
            ],
            "party": "PMDB"
        },
        {
            "deputyID": 1216,
            "scatterplot": [
                0.1153,
                -0.3285
            ],
            "party": "PSDB"
        },
        {
            "deputyID": 1217,
            "scatterplot": [
                0.129,
                -0.5485
            ],
            "party": "DEM"
        },
        {
            "deputyID": 1222,
            "scatterplot": [
                0.2418,
                -0.7195
            ],
            "party": "DEM"
        },
        {
            "deputyID": 1229,
            "scatterplot": [
                0.2365,
                -0.851
            ],
            "party": "DEM"
        },
        {
            "deputyID": 1231,
            "scatterplot": [
                -0.8067,
                -0.08008
            ],
            "party": "PT"
        },
        {
            "deputyID": 1233,
            "scatterplot": [
                -0.6168,
                0.06681
            ],
            "party": "PT"
        },
        {
            "deputyID": 1236,
            "scatterplot": [
                0.09058,
                -0.7218
            ],
            "party": "PSDB"
        },
        {
            "deputyID": 1238,
            "scatterplot": [
                -0.8304,
                -0.1042
            ],
            "party": "PMDB"
        },
        {
            "deputyID": 1241,
            "scatterplot": [
                -0.7106,
                0.04183
            ],
            "party": "PT"
        },
        {
            "deputyID": 1244,
            "scatterplot": [
                -0.9385,
                0.01652
            ],
            "party": "PT"
        },
        {
            "deputyID": 1249,
            "scatterplot": [
                -0.6169,
                -0.1759
            ],
            "party": "PTB"
        },
        {
            "deputyID": 1254,
            "scatterplot": [
                0.1878,
                -0.7606
            ],
            "party": "PSDB"
        },
        {
            "deputyID": 1258,
            "scatterplot": [
                -0.8078,
                -0.05996
            ],
            "party": "PMDB"
        },
        {
            "deputyID": 1259,
            "scatterplot": [
                -0.8851,
                -0.2557
            ],
            "party": "PP"
        },
        {
            "deputyID": 1260,
            "scatterplot": [
                -0.8251,
                0.05306
            ],
            "party": "PCdoB"
        },
        {
            "deputyID": 1261,
            "scatterplot": [
                -0.806,
                0.06051
            ],
            "party": "PT"
        },
        {
            "deputyID": 1268,
            "scatterplot": [
                0.2273,
                -0.8098
            ],
            "party": "DEM"
        },
        {
            "deputyID": 1270,
            "scatterplot": [
                -0.7779,
                0.09949
            ],
            "party": "PDT"
        },
        {
            "deputyID": 1276,
            "scatterplot": [
                -0.7315,
                -0.06129
            ],
            "party": "PP"
        },
        {
            "deputyID": 1279,
            "scatterplot": [
                -0.8134,
                0.05298
            ],
            "party": "PMN"
        },
        {
            "deputyID": 1281,
            "scatterplot": [
                0.2431,
                -0.7286
            ],
            "party": "PMDB"
        },
        {
            "deputyID": 1288,
            "scatterplot": [
                -0.8581,
                0.05272
            ],
            "party": "PSB"
        },
        {
            "deputyID": 1297,
            "scatterplot": [
                -0.7293,
                0.02771
            ],
            "party": "PP"
        },
        {
            "deputyID": 1299,
            "scatterplot": [
                -0.654,
                -0.0622
            ],
            "party": "PDT"
        },
        {
            "deputyID": 1308,
            "scatterplot": [
                -0.8688,
                -0.04113
            ],
            "party": "PCdoB"
        },
        {
            "deputyID": 1312,
            "scatterplot": [
                -0.6413,
                0.006805
            ],
            "party": "PMDB"
        },
        {
            "deputyID": 1313,
            "scatterplot": [
                -0.8371,
                -0.08267
            ],
            "party": "PP"
        },
        {
            "deputyID": 1316,
            "scatterplot": [
                0.1863,
                -0.93
            ],
            "party": "PSDB"
        },
        {
            "deputyID": 1318,
            "scatterplot": [
                0.1955,
                -0.9934
            ],
            "party": "PSDB"
        },
        {
            "deputyID": 1321,
            "scatterplot": [
                -0.6902,
                -0.132
            ],
            "party": "PMDB"
        },
        {
            "deputyID": 1324,
            "scatterplot": [
                -0.7843,
                0.05219
            ],
            "party": "PDT"
        },
        {
            "deputyID": 1325,
            "scatterplot": [
                -0.8053,
                0.02752
            ],
            "party": "PR"
        },
        {
            "deputyID": 1326,
            "scatterplot": [
                -0.2973,
                -0.02052
            ],
            "party": "PR"
        },
        {
            "deputyID": 1327,
            "scatterplot": [
                -0.8159,
                0.01675
            ],
            "party": "PT"
        },
        {
            "deputyID": 1328,
            "scatterplot": [
                -0.8133,
                -0.1864
            ],
            "party": "PHS"
        },
        {
            "deputyID": 1331,
            "scatterplot": [
                0.1174,
                -0.7071
            ],
            "party": "PSDB"
        },
        {
            "deputyID": 1338,
            "scatterplot": [
                -0.4262,
                -0.05953
            ],
            "party": "PSB"
        },
        {
            "deputyID": 1339,
            "scatterplot": [
                0.1923,
                -0.6476
            ],
            "party": "PPS"
        },
        {
            "deputyID": 1342,
            "scatterplot": [
                0.1469,
                -0.8123
            ],
            "party": "PSDB"
        },
        {
            "deputyID": 1343,
            "scatterplot": [
                0.2073,
                -0.3546
            ],
            "party": "PSDB"
        },
        {
            "deputyID": 1346,
            "scatterplot": [
                0.2441,
                -0.7753
            ],
            "party": "DEM"
        },
        {
            "deputyID": 1347,
            "scatterplot": [
                -0.7182,
                0.1024
            ],
            "party": "PDT"
        },
        {
            "deputyID": 1350,
            "scatterplot": [
                -0.3869,
                -0.03112
            ],
            "party": "PSB"
        },
        {
            "deputyID": 1351,
            "scatterplot": [
                -0.4465,
                0.1106
            ],
            "party": "PDT"
        },
        {
            "deputyID": 1355,
            "scatterplot": [
                0.1102,
                -0.7151
            ],
            "party": "PSDB"
        },
        {
            "deputyID": 1357,
            "scatterplot": [
                -0.6262,
                0.03994
            ],
            "party": "PT"
        },
        {
            "deputyID": 1361,
            "scatterplot": [
                -0.5895,
                -0.1956
            ],
            "party": "PMDB"
        },
        {
            "deputyID": 1362,
            "scatterplot": [
                -0.8707,
                -0.1445
            ],
            "party": "PP"
        },
        {
            "deputyID": 1368,
            "scatterplot": [
                -0.7351,
                -0.2434
            ],
            "party": "PMDB"
        },
        {
            "deputyID": 1373,
            "scatterplot": [
                -0.7962,
                -0.04638
            ],
            "party": "PT"
        },
        {
            "deputyID": 1374,
            "scatterplot": [
                0.1746,
                -0.7863
            ],
            "party": "PSDB"
        },
        {
            "deputyID": 1375,
            "scatterplot": [
                -0.8466,
                0.03429
            ],
            "party": "PT"
        },
        {
            "deputyID": 1382,
            "scatterplot": [
                -0.7836,
                -0.1313
            ],
            "party": "PMDB"
        },
        {
            "deputyID": 1392,
            "scatterplot": [
                -0.8473,
                -0.02456
            ],
            "party": "PCdoB"
        },
        {
            "deputyID": 1397,
            "scatterplot": [
                -0.6795,
                -0.1402
            ],
            "party": "PP"
        },
        {
            "deputyID": 1398,
            "scatterplot": [
                -0.7506,
                -0.1842
            ],
            "party": "PDT"
        },
        {
            "deputyID": 1400,
            "scatterplot": [
                -0.8105,
                -0.2097
            ],
            "party": "PP"
        },
        {
            "deputyID": 1402,
            "scatterplot": [
                0.2054,
                -0.8969
            ],
            "party": "PSDB"
        },
        {
            "deputyID": 1403,
            "scatterplot": [
                -0.8024,
                0.02439
            ],
            "party": "PDT"
        },
        {
            "deputyID": 1405,
            "scatterplot": [
                -0.8732,
                -0.03578
            ],
            "party": "PSB"
        },
        {
            "deputyID": 1407,
            "scatterplot": [
                -0.568,
                -0.05365
            ],
            "party": "PMDB"
        },
        {
            "deputyID": 1409,
            "scatterplot": [
                0.2095,
                -0.6974
            ],
            "party": "DEM"
        },
        {
            "deputyID": 1425,
            "scatterplot": [
                -0.7624,
                -0.004554
            ],
            "party": "PMN"
        },
        {
            "deputyID": 1429,
            "scatterplot": [
                -0.8758,
                0.002389
            ],
            "party": "PT"
        },
        {
            "deputyID": 1431,
            "scatterplot": [
                0.1914,
                -0.6342
            ],
            "party": "DEM"
        },
        {
            "deputyID": 1433,
            "scatterplot": [
                -0.4454,
                -0.121
            ],
            "party": "PMDB"
        },
        {
            "deputyID": 1495,
            "scatterplot": [
                -0.8971,
                -0.1105
            ],
            "party": "PR"
        },
        {
            "deputyID": 1508,
            "scatterplot": [
                -0.6484,
                -0.0847
            ],
            "party": "PMDB"
        },
        {
            "deputyID": 1512,
            "scatterplot": [
                -0.8905,
                -0.1968
            ],
            "party": "PP"
        },
        {
            "deputyID": 1521,
            "scatterplot": [
                -0.751,
                -0.07908
            ],
            "party": "PT"
        },
        {
            "deputyID": 1522,
            "scatterplot": [
                -0.8503,
                0.1062
            ],
            "party": "PT"
        },
        {
            "deputyID": 1528,
            "scatterplot": [
                -0.6143,
                -0.08409
            ],
            "party": "PMN"
        },
        {
            "deputyID": 1529,
            "scatterplot": [
                -0.6799,
                -0.04441
            ],
            "party": "PSB"
        },
        {
            "deputyID": 1560,
            "scatterplot": [
                -0.7456,
                -0.1876
            ],
            "party": "PR"
        },
        {
            "deputyID": 1562,
            "scatterplot": [
                0.2317,
                -0.7413
            ],
            "party": "DEM"
        },
        {
            "deputyID": 1591,
            "scatterplot": [
                -0.4884,
                -0.1181
            ],
            "party": "PP"
        },
        {
            "deputyID": 1592,
            "scatterplot": [
                -0.7451,
                -0.05286
            ],
            "party": "PT"
        },
        {
            "deputyID": 1617,
            "scatterplot": [
                -0.7268,
                -0.1699
            ],
            "party": "PMDB"
        },
        {
            "deputyID": 1637,
            "scatterplot": [
                -0.8446,
                -0.02412
            ],
            "party": "PT"
        },
        {
            "deputyID": 1646,
            "scatterplot": [
                -0.8235,
                -0.01663
            ],
            "party": "PT"
        },
        {
            "deputyID": 1647,
            "scatterplot": [
                -0.7722,
                -0.2828
            ],
            "party": "PTB"
        },
        {
            "deputyID": 1740,
            "scatterplot": [
                -0.7306,
                -0.02983
            ],
            "party": "PDT"
        },
        {
            "deputyID": 1741,
            "scatterplot": [
                0.181,
                -0.7452
            ],
            "party": "PPS"
        },
        {
            "deputyID": 1748,
            "scatterplot": [
                -0.6237,
                -0.1071
            ],
            "party": "PR"
        },
        {
            "deputyID": 1750,
            "scatterplot": [
                -0.8308,
                0.02585
            ],
            "party": "PCdoB"
        },
        {
            "deputyID": 1752,
            "scatterplot": [
                -0.71,
                -0.09219
            ],
            "party": "PSB"
        },
        {
            "deputyID": 1753,
            "scatterplot": [
                0.1845,
                -1.002
            ],
            "party": "PSDB"
        },
        {
            "deputyID": 1755,
            "scatterplot": [
                -0.7885,
                -0.01695
            ],
            "party": "PSB"
        },
        {
            "deputyID": 1758,
            "scatterplot": [
                -0.595,
                -0.06559
            ],
            "party": "PP"
        },
        {
            "deputyID": 1759,
            "scatterplot": [
                -0.8139,
                0.00813
            ],
            "party": "PSC"
        },
        {
            "deputyID": 1760,
            "scatterplot": [
                -0.8202,
                -0.09814
            ],
            "party": "PSC"
        },
        {
            "deputyID": 1764,
            "scatterplot": [
                -0.7621,
                -0.2833
            ],
            "party": "PMDB"
        },
        {
            "deputyID": 1765,
            "scatterplot": [
                -0.896,
                -0.02326
            ],
            "party": "PT"
        },
        {
            "deputyID": 1768,
            "scatterplot": [
                -0.8911,
                -0.1676
            ],
            "party": "PV"
        },
        {
            "deputyID": 1770,
            "scatterplot": [
                -0.8449,
                0.02746
            ],
            "party": "PT"
        },
        {
            "deputyID": 1771,
            "scatterplot": [
                -0.6871,
                -0.03384
            ],
            "party": "PSB"
        },
        {
            "deputyID": 1772,
            "scatterplot": [
                -0.7782,
                0.005678
            ],
            "party": "PT"
        },
        {
            "deputyID": 1776,
            "scatterplot": [
                -0.7915,
                0.04784
            ],
            "party": "PT"
        },
        {
            "deputyID": 1819,
            "scatterplot": [
                0.2592,
                -0.8376
            ],
            "party": "DEM"
        },
        {
            "deputyID": 1820,
            "scatterplot": [
                0.197,
                -0.9395
            ],
            "party": "PSDB"
        },
        {
            "deputyID": 1822,
            "scatterplot": [
                -0.8267,
                -0.01805
            ],
            "party": "PRB"
        },
        {
            "deputyID": 1823,
            "scatterplot": [
                0.1612,
                -1.06
            ],
            "party": "PSDB"
        },
        {
            "deputyID": 1824,
            "scatterplot": [
                0.1841,
                -0.6044
            ],
            "party": "DEM"
        },
        {
            "deputyID": 1830,
            "scatterplot": [
                -0.6301,
                -0.2279
            ],
            "party": "PR"
        },
        {
            "deputyID": 1831,
            "scatterplot": [
                -0.8019,
                0.004531
            ],
            "party": "PV"
        },
        {
            "deputyID": 1835,
            "scatterplot": [
                0.1926,
                -0.9025
            ],
            "party": "PSDB"
        },
        {
            "deputyID": 1838,
            "scatterplot": [
                -0.6062,
                -0.1062
            ],
            "party": "PP"
        },
        {
            "deputyID": 1844,
            "scatterplot": [
                0.2454,
                -0.7741
            ],
            "party": "DEM"
        },
        {
            "deputyID": 1845,
            "scatterplot": [
                0.1621,
                -0.7894
            ],
            "party": "DEM"
        },
        {
            "deputyID": 1846,
            "scatterplot": [
                -0.5612,
                -0.07382
            ],
            "party": "DEM"
        },
        {
            "deputyID": 1850,
            "scatterplot": [
                0.1353,
                -0.9197
            ],
            "party": "PSDB"
        },
        {
            "deputyID": 1853,
            "scatterplot": [
                0.07772,
                -0.6215
            ],
            "party": "PSDB"
        },
        {
            "deputyID": 1894,
            "scatterplot": [
                -0.5422,
                -0.2475
            ],
            "party": "PP"
        },
        {
            "deputyID": 1899,
            "scatterplot": [
                -0.6254,
                0.01408
            ],
            "party": "PV"
        },
        {
            "deputyID": 1900,
            "scatterplot": [
                -0.711,
                0.02722
            ],
            "party": "PT"
        },
        {
            "deputyID": 1901,
            "scatterplot": [
                -0.01943,
                -0.5172
            ],
            "party": "PPS"
        },
        {
            "deputyID": 1902,
            "scatterplot": [
                -0.6624,
                0.03651
            ],
            "party": "PMN"
        },
        {
            "deputyID": 1903,
            "scatterplot": [
                -0.8132,
                0.02669
            ],
            "party": "PCdoB"
        },
        {
            "deputyID": 1904,
            "scatterplot": [
                -0.8075,
                -0.04892
            ],
            "party": "PP"
        },
        {
            "deputyID": 1905,
            "scatterplot": [
                -0.6039,
                -0.3004
            ],
            "party": "PSC"
        },
        {
            "deputyID": 1906,
            "scatterplot": [
                -0.7197,
                -0.04288
            ],
            "party": "PMDB"
        },
        {
            "deputyID": 1907,
            "scatterplot": [
                -0.3378,
                -0.009438
            ],
            "party": "PPS"
        },
        {
            "deputyID": 1908,
            "scatterplot": [
                -0.7071,
                0.04793
            ],
            "party": "PV"
        },
        {
            "deputyID": 1909,
            "scatterplot": [
                -0.8569,
                0.0286
            ],
            "party": "PT"
        },
        {
            "deputyID": 1910,
            "scatterplot": [
                -0.6496,
                -0.14
            ],
            "party": "PMDB"
        },
        {
            "deputyID": 1911,
            "scatterplot": [
                -0.5348,
                -0.0888
            ],
            "party": "PV"
        },
        {
            "deputyID": 1912,
            "scatterplot": [
                -0.8619,
                -0.04269
            ],
            "party": "PDT"
        },
        {
            "deputyID": 1913,
            "scatterplot": [
                -0.887,
                -0.04854
            ],
            "party": "PT"
        },
        {
            "deputyID": 1914,
            "scatterplot": [
                0.1988,
                -0.7532
            ],
            "party": "PSDB"
        },
        {
            "deputyID": 1915,
            "scatterplot": [
                -0.3056,
                -0.3536
            ],
            "party": "PMDB"
        },
        {
            "deputyID": 1917,
            "scatterplot": [
                -0.5301,
                -0.006476
            ],
            "party": "PR"
        },
        {
            "deputyID": 1928,
            "scatterplot": [
                -0.8353,
                0.006838
            ],
            "party": "PT"
        },
        {
            "deputyID": 1929,
            "scatterplot": [
                -0.7603,
                -0.222
            ],
            "party": "PP"
        },
        {
            "deputyID": 1930,
            "scatterplot": [
                -0.8015,
                -0.07403
            ],
            "party": "PR"
        },
        {
            "deputyID": 1931,
            "scatterplot": [
                -0.7104,
                -0.1794
            ],
            "party": "PMDB"
        },
        {
            "deputyID": 1932,
            "scatterplot": [
                -0.7616,
                -0.01679
            ],
            "party": "PSB"
        },
        {
            "deputyID": 1933,
            "scatterplot": [
                -0.7029,
                -0.2786
            ],
            "party": "PP"
        },
        {
            "deputyID": 1934,
            "scatterplot": [
                -0.3257,
                -0.4784
            ],
            "party": "PSB"
        },
        {
            "deputyID": 1935,
            "scatterplot": [
                0.2353,
                -0.8449
            ],
            "party": "DEM"
        },
        {
            "deputyID": 1936,
            "scatterplot": [
                -0.7807,
                -0.1393
            ],
            "party": "PSB"
        },
        {
            "deputyID": 1937,
            "scatterplot": [
                -0.7698,
                -0.2583
            ],
            "party": "PMDB"
        },
        {
            "deputyID": 1938,
            "scatterplot": [
                0.1878,
                -0.7095
            ],
            "party": "DEM"
        },
        {
            "deputyID": 1939,
            "scatterplot": [
                -0.8278,
                -0.1285
            ],
            "party": "PR"
        },
        {
            "deputyID": 1940,
            "scatterplot": [
                -0.8234,
                0.07459
            ],
            "party": "PDT"
        },
        {
            "deputyID": 1941,
            "scatterplot": [
                -0.4692,
                0.07936
            ],
            "party": "PSB"
        },
        {
            "deputyID": 1942,
            "scatterplot": [
                -0.9123,
                -0.1334
            ],
            "party": "PMDB"
        },
        {
            "deputyID": 1943,
            "scatterplot": [
                -0.7679,
                -0.08496
            ],
            "party": "PMDB"
        },
        {
            "deputyID": 1944,
            "scatterplot": [
                0.1605,
                -0.7933
            ],
            "party": "PSDB"
        },
        {
            "deputyID": 1945,
            "scatterplot": [
                -0.7918,
                -0.1008
            ],
            "party": "PMDB"
        },
        {
            "deputyID": 1946,
            "scatterplot": [
                -0.6676,
                0.1009
            ],
            "party": "PSB"
        },
        {
            "deputyID": 1947,
            "scatterplot": [
                -0.2982,
                0.1054
            ],
            "party": "PT"
        },
        {
            "deputyID": 1948,
            "scatterplot": [
                -0.162,
                -0.508
            ],
            "party": "PMDB"
        },
        {
            "deputyID": 1949,
            "scatterplot": [
                -0.6618,
                0.003807
            ],
            "party": "PRB"
        },
        {
            "deputyID": 1950,
            "scatterplot": [
                -0.9192,
                -0.1739
            ],
            "party": "PMDB"
        },
        {
            "deputyID": 1951,
            "scatterplot": [
                -0.7713,
                -0.2019
            ],
            "party": "PMDB"
        },
        {
            "deputyID": 1952,
            "scatterplot": [
                0.215,
                -0.9352
            ],
            "party": "PSDB"
        },
        {
            "deputyID": 1953,
            "scatterplot": [
                -0.889,
                -0.1121
            ],
            "party": "PT"
        },
        {
            "deputyID": 1954,
            "scatterplot": [
                -0.6104,
                -0.127
            ],
            "party": "PSB"
        },
        {
            "deputyID": 1955,
            "scatterplot": [
                -0.9736,
                -0.01115
            ],
            "party": "PT"
        },
        {
            "deputyID": 1956,
            "scatterplot": [
                -0.5471,
                -0.2023
            ],
            "party": "PR"
        },
        {
            "deputyID": 1957,
            "scatterplot": [
                -0.8201,
                -0.133
            ],
            "party": "PMDB"
        },
        {
            "deputyID": 1958,
            "scatterplot": [
                -0.745,
                -0.05415
            ],
            "party": "PV"
        },
        {
            "deputyID": 1959,
            "scatterplot": [
                -0.6731,
                -0.142
            ],
            "party": "PRTB"
        },
        {
            "deputyID": 1960,
            "scatterplot": [
                -0.8236,
                -0.01752
            ],
            "party": "PT"
        },
        {
            "deputyID": 1961,
            "scatterplot": [
                -0.7659,
                -0.1352
            ],
            "party": "PSC"
        },
        {
            "deputyID": 1962,
            "scatterplot": [
                0.1866,
                -0.9351
            ],
            "party": "PSDB"
        },
        {
            "deputyID": 1963,
            "scatterplot": [
                -0.658,
                -0.02583
            ],
            "party": "PDT"
        },
        {
            "deputyID": 1964,
            "scatterplot": [
                -0.8286,
                -0.04854
            ],
            "party": "PCdoB"
        },
        {
            "deputyID": 1965,
            "scatterplot": [
                -0.8778,
                -0.1189
            ],
            "party": "PMDB"
        },
        {
            "deputyID": 1966,
            "scatterplot": [
                0.1399,
                -0.4329
            ],
            "party": "DEM"
        },
        {
            "deputyID": 1967,
            "scatterplot": [
                0.1999,
                -0.68
            ],
            "party": "PPS"
        },
        {
            "deputyID": 1968,
            "scatterplot": [
                -0.7701,
                -0.002105
            ],
            "party": "PRB"
        },
        {
            "deputyID": 1969,
            "scatterplot": [
                -0.5567,
                -0.2941
            ],
            "party": "PMDB"
        },
        {
            "deputyID": 1971,
            "scatterplot": [
                -0.6881,
                -0.02208
            ],
            "party": "PR"
        },
        {
            "deputyID": 1972,
            "scatterplot": [
                -0.6544,
                -0.1212
            ],
            "party": "PMDB"
        },
        {
            "deputyID": 1973,
            "scatterplot": [
                0.1863,
                -0.5711
            ],
            "party": "DEM"
        },
        {
            "deputyID": 1974,
            "scatterplot": [
                -0.7342,
                -0.1031
            ],
            "party": "PR"
        },
        {
            "deputyID": 1975,
            "scatterplot": [
                -0.8038,
                -0.2035
            ],
            "party": "PTdoB"
        },
        {
            "deputyID": 1976,
            "scatterplot": [
                -0.2679,
                -0.1379
            ],
            "party": "PR"
        },
        {
            "deputyID": 1977,
            "scatterplot": [
                -0.445,
                -0.2797
            ],
            "party": "PV"
        },
        {
            "deputyID": 1978,
            "scatterplot": [
                0.2326,
                -0.9874
            ],
            "party": "PSDB"
        },
        {
            "deputyID": 1979,
            "scatterplot": [
                0.1914,
                -0.9996
            ],
            "party": "PSDB"
        },
        {
            "deputyID": 1980,
            "scatterplot": [
                -0.7455,
                -0.2092
            ],
            "party": "PTB"
        },
        {
            "deputyID": 1981,
            "scatterplot": [
                -0.7425,
                0.03522
            ],
            "party": "PT"
        },
        {
            "deputyID": 1982,
            "scatterplot": [
                0.2145,
                -0.7168
            ],
            "party": "PSDB"
        },
        {
            "deputyID": 1983,
            "scatterplot": [
                -0.7296,
                -0.01957
            ],
            "party": "PDT"
        },
        {
            "deputyID": 1984,
            "scatterplot": [
                0.2366,
                -0.8844
            ],
            "party": "PSDB"
        },
        {
            "deputyID": 1985,
            "scatterplot": [
                -0.6822,
                0.1018
            ],
            "party": "PR"
        },
        {
            "deputyID": 1986,
            "scatterplot": [
                -0.8154,
                0.02071
            ],
            "party": "PSB"
        },
        {
            "deputyID": 1987,
            "scatterplot": [
                -0.6642,
                -0.1165
            ],
            "party": "PMDB"
        },
        {
            "deputyID": 1988,
            "scatterplot": [
                -0.8399,
                -0.1174
            ],
            "party": "PDT"
        },
        {
            "deputyID": 1989,
            "scatterplot": [
                0.1846,
                -0.6873
            ],
            "party": "PSDB"
        },
        {
            "deputyID": 1990,
            "scatterplot": [
                0.2484,
                -0.7912
            ],
            "party": "DEM"
        },
        {
            "deputyID": 1991,
            "scatterplot": [
                0.1527,
                -0.9053
            ],
            "party": "DEM"
        },
        {
            "deputyID": 1992,
            "scatterplot": [
                -0.8602,
                -0.2804
            ],
            "party": "PP"
        },
        {
            "deputyID": 1993,
            "scatterplot": [
                -0.4901,
                -0.1186
            ],
            "party": "PSB"
        },
        {
            "deputyID": 1994,
            "scatterplot": [
                -0.7827,
                -0.04179
            ],
            "party": "PR"
        },
        {
            "deputyID": 1995,
            "scatterplot": [
                -0.8169,
                -0.1683
            ],
            "party": "PTB"
        },
        {
            "deputyID": 1996,
            "scatterplot": [
                0.207,
                -0.6922
            ],
            "party": "DEM"
        },
        {
            "deputyID": 1997,
            "scatterplot": [
                -0.9282,
                -0.143
            ],
            "party": "PTB"
        },
        {
            "deputyID": 1998,
            "scatterplot": [
                -0.5703,
                0.07915
            ],
            "party": "PSB"
        },
        {
            "deputyID": 2000,
            "scatterplot": [
                0.1191,
                -0.9758
            ],
            "party": "PSDB"
        },
        {
            "deputyID": 2001,
            "scatterplot": [
                -0.5402,
                -0.1331
            ],
            "party": "PMDB"
        },
        {
            "deputyID": 2002,
            "scatterplot": [
                -0.9058,
                0.02614
            ],
            "party": "PT"
        },
        {
            "deputyID": 2003,
            "scatterplot": [
                0.1429,
                -0.6601
            ],
            "party": "DEM"
        },
        {
            "deputyID": 2004,
            "scatterplot": [
                -0.8868,
                0.008981
            ],
            "party": "PT"
        },
        {
            "deputyID": 2005,
            "scatterplot": [
                -0.9211,
                -0.01859
            ],
            "party": "PSB"
        },
        {
            "deputyID": 2006,
            "scatterplot": [
                -0.7477,
                -0.1173
            ],
            "party": "PV"
        },
        {
            "deputyID": 2007,
            "scatterplot": [
                -0.5718,
                0.08559
            ],
            "party": "PR"
        },
        {
            "deputyID": 2008,
            "scatterplot": [
                0.1636,
                -0.2479
            ],
            "party": "DEM"
        },
        {
            "deputyID": 2079,
            "scatterplot": [
                -0.7328,
                -0.01473
            ],
            "party": "PTB"
        },
        {
            "deputyID": 2080,
            "scatterplot": [
                -0.3138,
                -0.07749
            ],
            "party": "PT"
        },
        {
            "deputyID": 2081,
            "scatterplot": [
                -0.8398,
                -0.1674
            ],
            "party": "PMDB"
        },
        {
            "deputyID": 2082,
            "scatterplot": [
                -0.4618,
                -0.2236
            ],
            "party": "PV"
        },
        {
            "deputyID": 2083,
            "scatterplot": [
                0.1903,
                -0.8849
            ],
            "party": "PSDB"
        },
        {
            "deputyID": 2085,
            "scatterplot": [
                0.2582,
                -0.8406
            ],
            "party": "PSDB"
        },
        {
            "deputyID": 2086,
            "scatterplot": [
                0.05109,
                -0.3726
            ],
            "party": "DEM"
        },
        {
            "deputyID": 2110,
            "scatterplot": [
                -0.4312,
                -0.1126
            ],
            "party": "PR"
        },
        {
            "deputyID": 2116,
            "scatterplot": [
                -0.5886,
                -0.2183
            ],
            "party": "PSC"
        },
        {
            "deputyID": 2154,
            "scatterplot": [
                -0.588,
                -0.01543
            ],
            "party": "PHS"
        },
        {
            "deputyID": 2155,
            "scatterplot": [
                -0.7173,
                0.02369
            ],
            "party": "PTB"
        },
        {
            "deputyID": 2156,
            "scatterplot": [
                -0.4194,
                0.1245
            ],
            "party": "DEM"
        },
        {
            "deputyID": 2164,
            "scatterplot": [
                -0.6452,
                -0.03854
            ],
            "party": "PR"
        },
        {
            "deputyID": 2165,
            "scatterplot": [
                0.2478,
                -0.6915
            ],
            "party": "DEM"
        },
        {
            "deputyID": 2171,
            "scatterplot": [
                -0.3965,
                -0.1303
            ],
            "party": "PP"
        },
        {
            "deputyID": 2172,
            "scatterplot": [
                -0.4791,
                -0.03805
            ],
            "party": "PV"
        },
        {
            "deputyID": 2415,
            "scatterplot": [
                -0.2197,
                -0.01822
            ],
            "party": "PMDB"
        },
        {
            "deputyID": 2429,
            "scatterplot": [
                0.004508,
                -0.5602
            ],
            "party": "PSDB"
        },
        {
            "deputyID": 2434,
            "scatterplot": [
                0.0934,
                -0.4383
            ],
            "party": "DEM"
        },
        {
            "deputyID": 2435,
            "scatterplot": [
                -0.5339,
                -0.1958
            ],
            "party": "PMDB"
        },
        {
            "deputyID": 2439,
            "scatterplot": [
                -0.7855,
                0.0121
            ],
            "party": "PT"
        },
        {
            "deputyID": 2440,
            "scatterplot": [
                0.04678,
                -0.7332
            ],
            "party": "PSDB"
        }
    ]
}